MANIFEST.in
README
_version.py
setup.cfg
setup.py
dark/__init__.py
dark/aggregates.py
dark/discovery.py
dark/shaping.py
dark.egg-info/PKG-INFO
dark.egg-info/SOURCES.txt
dark.egg-info/dependency_links.txt
dark.egg-info/top_level.txt