Metadata-Version: 1.1
Name: dark
Version: 0.7.1
Summary: Data Analysis and Reporting Kit (DARK)
Home-page: http://bitbucket.org/neithere/dark/
Author: Andrey Mikhailenko
Author-email: andy@neithere.net
License: GNU Lesser General Public License (LGPL), Version 3
Download-URL: http://bitbucket.org/neithere/dark/src/
Keywords: data analysis mining reporting pivot query database
Platform: UNKNOWN
Classifier: Development Status :: 3 - Alpha
Classifier: Environment :: Console
Classifier: Environment :: Plugins
Classifier: Intended Audience :: Developers
Classifier: Intended Audience :: Education
Classifier: Intended Audience :: Information Technology
Classifier: Intended Audience :: Science/Research
Classifier: License :: OSI Approved :: GNU Library or Lesser General Public License (LGPL)
Classifier: Programming Language :: Python
Classifier: Topic :: Database
Classifier: Topic :: Database :: Database Engines/Servers
Classifier: Topic :: Database :: Front-Ends
Classifier: Topic :: Office/Business :: Financial :: Spreadsheet
Classifier: Topic :: Software Development :: Libraries :: Python Modules
Requires: python (>= 2.5)
Requires: doqu (>= 0.25)
Provides: dark
Obsoletes: datashaping
